setup.cfg
setup.py
pysharedutils/__init__.py
pysharedutils/attrs.py
pysharedutils/dates.py
pysharedutils/decorators.py
pysharedutils/dicts.py
pysharedutils/encodings.py
pysharedutils/functions.py
pysharedutils/ittrs.py
pysharedutils/lists.py
pysharedutils/strings.py
pysharedutils.egg-info/PKG-INFO
pysharedutils.egg-info/SOURCES.txt
pysharedutils.egg-info/dependency_links.txt
pysharedutils.egg-info/requires.txt
pysharedutils.egg-info/top_level.txt